agcombine/__init__.py
agcombine/agcombine.py
agcombine/common.py
agcombine-0.0.1.dist-info/licenses/LICENSE
agcombine-0.0.1.dist-info/METADATA
agcombine-0.0.1.dist-info/WHEEL
agcombine-0.0.1.dist-info/entry_points.txt
agcombine-0.0.1.dist-info/top_level.txt
agcombine-0.0.1.dist-info/RECORD
